tea_client/__init__.py
tea_client/client.py
tea_client/config.py
tea_client/errors.py
tea_client/handler.py
tea_client/http.py
tea_client/models.py
tea_client/version.py
tea_client-0.0.8.dist-info/AUTHORS
tea_client-0.0.8.dist-info/LICENSE
tea_client-0.0.8.dist-info/METADATA
tea_client-0.0.8.dist-info/WHEEL
tea_client-0.0.8.dist-info/top_level.txt
tea_client-0.0.8.dist-info/RECORD
